usefulgen/__init__.py
usefulgen/modules/__init__.py
usefulgen/modules/basic.py
usefulgen/modules/email.py
usefulgen/modules/wordlist.py
usefulgen-1.0.4.0.dist-info/LICENSE
usefulgen-1.0.4.0.dist-info/METADATA
usefulgen-1.0.4.0.dist-info/WHEEL
usefulgen-1.0.4.0.dist-info/top_level.txt
usefulgen-1.0.4.0.dist-info/RECORD
