Metadata-Version: 2.1
Name: usefulgen
Version: 1.0.4.0
Summary: Python Module dedicated to time-saving generators, made by M4elstr0m
Home-page: https://github.com/M4elstr0m/UsefulGenPy
Download-URL: https://pypi.org/project/usefulgen/
Author: M4elstr0m
Classifier: Programming Language :: Python :: 3
Classifier: License :: OSI Approved :: MIT License
License-File: LICENSE
Requires-Dist: typing
